mecapacktools/__init__.py
mecapacktools/libCfg.py
mecapacktools/libExcel.py
mecapacktools/libFTP.py
mecapacktools/libLog.py
mecapacktools/libMail.py
mecapacktools/libSql.py
mecapacktools/libTool.py
mecapacktools/libWebServices.py
mecapacktools/libXlsx.py
mecapacktools-1.3.28.dist-info/LICENSE
mecapacktools-1.3.28.dist-info/METADATA
mecapacktools-1.3.28.dist-info/WHEEL
mecapacktools-1.3.28.dist-info/RECORD
